Metadata-Version: 2.1
Name: fernanda
Version: 0.1
Summary: Juego que nos ayuda a ver nuestro nivel de aprendizaje
Home-page: https://github.com/12silvia/repositorio
Author: Silvia leon
License: MIT
